django_ordered_field/__init__.py
django_ordered_field/common.py
django_ordered_field/ordered_collection_field.py
django_ordered_field/ordered_field.py
django_ordered_field/signals.py
django_ordered_field-1.0.0.dist-info/METADATA
django_ordered_field-1.0.0.dist-info/RECORD
django_ordered_field-1.0.0.dist-info/WHEEL
django_ordered_field-1.0.0.dist-info/top_level.txt
