Metadata-Version: 2.1
Name: django-ordered-field
Version: 1.0.0
Summary: Django field to help arrange model instances in an ordered fashion
Home-page: https://github.com/kimgea/django-ordered-field
Author: Kim-Georg Aase
Author-email: kim.georg.aase@gmail.com
License: MIT
Keywords: django-ordered-field
Platform: UNKNOWN
Classifier: Development Status :: 4 - Beta
Classifier: Environment :: Web Environment
Classifier: Framework :: Django :: 2.0
Classifier: Framework :: Django :: 2.1
Classifier: Intended Audience :: Developers
Classifier: License :: OSI Approved :: BSD License
Classifier: Natural Language :: English
Classifier: Programming Language :: Python :: 3.6
Classifier: Topic :: Internet :: WWW/HTTP
